MANIFEST.in
grafcli.conf.example
setup.py
grafcli/__init__.py
grafcli/args.py
grafcli/commands.py
grafcli/completer.py
grafcli/core.py
grafcli/documents.py
grafcli/exceptions.py
grafcli/utils.py
grafcli/version.py
grafcli.egg-info/PKG-INFO
grafcli.egg-info/SOURCES.txt
grafcli.egg-info/dependency_links.txt
grafcli.egg-info/requires.txt
grafcli.egg-info/top_level.txt
grafcli/resources/__init__.py
grafcli/resources/common.py
grafcli/resources/local.py
grafcli/resources/remote.py
grafcli/resources/resources.py
grafcli/resources/templates.py
grafcli/storage/__init__.py
grafcli/storage/api.py
grafcli/storage/elastic.py
grafcli/storage/sql.py
grafcli/storage/storage.py
grafcli/storage/system.py
scripts/grafcli