Metadata-Version: 1.1
Name: grafcli
Version: 0.5.9
Summary: Grafana CLI management tool
Home-page: https://github.com/m110/grafcli
Author: Milosz Smolka
Author-email: m110@m110.pl
License: UNKNOWN
Platform: UNKNOWN
Classifier: Development Status :: 3 - Alpha
Classifier: Environment :: Console
Classifier: Intended Audience :: End Users/Desktop
Classifier: Intended Audience :: Developers
Classifier: Intended Audience :: System Administrators
Classifier: License :: OSI Approved :: MIT License
Classifier: Operating System :: POSIX
Classifier: Programming Language :: Python :: 3.4
Classifier: Topic :: System :: Systems Administration
